translate_md/__init__.py
translate_md/client.py
translate_md/logger.py
translate_md/main.py
translate_md/markdown.py
translate_md/py.typed
translate_md-0.0.1.dist-info/METADATA
translate_md-0.0.1.dist-info/WHEEL
translate_md-0.0.1.dist-info/entry_points.txt
translate_md-0.0.1.dist-info/licenses/LICENSE
translate_md-0.0.1.dist-info/RECORD
