Metadata-Version: 2.1
Name: translate_md
Version: 0.0.1
Summary: Python client to translate markdown files from englisth to spanish
Project-URL: Source, https://github.com/plaguss/translate-md
Author-email: Agustín Piqueres <agustin.piqueres@gmail.com>
License:                     GNU GENERAL PUBLIC LICENSE
License-File: LICENSE
Classifier: Intended Audience :: Developers
Classifier: License :: OSI Approved :: GNU General Public License v3 or later (GPLv3+)
Classifier: Natural Language :: English
Classifier: Programming Language :: Python :: 3.10
Classifier: Programming Language :: Python :: Implementation :: CPython
Requires-Python: >=3.10
Requires-Dist: markdown-it-py>=2.2.0
Requires-Dist: mdformat>=0.7.16
Requires-Dist: requests>=2.28.2
Provides-Extra: cli
Requires-Dist: rich>=13.3.2; extra == 'cli'
Requires-Dist: typer>=0.7.0; extra == 'cli'
Provides-Extra: dev
Requires-Dist: black; extra == 'dev'
Requires-Dist: mypy; extra == 'dev'
Requires-Dist: ruff; extra == 'dev'
Provides-Extra: test
Requires-Dist: coverage>=7.1.0; extra == 'test'
Requires-Dist: nox>=2022.11.21; extra == 'test'
Requires-Dist: pytest-cov>=4.0.0; extra == 'test'
Requires-Dist: pytest-mock>=3.10.0; extra == 'test'
Requires-Dist: pytest>=7.2.0; extra == 'test'
